icloudservice/__init__.py
icloudservice/icloudservice.py
icloudservice/src/__init__.py
icloudservice/src/provider/__init__.py
icloudservice/src/provider/aws/__init__.py
icloudservice/src/provider/aws/aws_provider.py
icloudservice/src/provider/azure/__init__.py
icloudservice/src/provider/azure/azure_provider.py
icloudservice/src/service/aws/aws_services.py
icloudservice/src/service/azure/__init__.py
icloudservice/src/service/azure/azure_services.py
icloudservice/src/tools/util.py
icloudservice/src/tools/format/color_text.py
icloudservice/src/tools/format/table_formatter.py
icloudservice/src/tools/format/table_render.py
icloudservice/src/tools/handler/table_data.py
icloudservice/src/tools/print/console.py
icloudservice/src/tools/progress/progress.py
icloudservice-0.9.3.dist-info/METADATA
icloudservice-0.9.3.dist-info/WHEEL
icloudservice-0.9.3.dist-info/top_level.txt
icloudservice-0.9.3.dist-info/RECORD
