Metadata-Version: 2.1
Name: icloudservice
Version: 0.9.3
Summary: The `icloudservice` class provides a Python interface for interacting with
Home-page: https://github.com/leonardogonzalolaura/workspace_icloudservice
Author: Leonardo Daniel Gonzalo Laura
Author-email: glleonardodaniel@gmail.com
License: MIT
Requires-Dist: botocore
Requires-Dist: azure-storage-blob
Requires-Dist: azure-servicebus
Requires-Dist: azure-identity
Requires-Dist: azure-cosmos
